visionclick/__init__.py
visionclick-0.1.0.dist-info/METADATA
visionclick-0.1.0.dist-info/WHEEL
visionclick-0.1.0.dist-info/entry_points.txt
visionclick-0.1.0.dist-info/top_level.txt
visionclick-0.1.0.dist-info/RECORD
