Metadata-Version: 2.4
Name: visionclick
Version: 0.1.0
Summary: A Python library for GUI automation with visual feedback
Home-page: https://github.com/kakuzu-aon/visionclick
Author: Kakuzu
Author-email: kakuzu.aon@gmail.com
Classifier: Development Status :: 3 - Alpha
Classifier: Intended Audience :: Developers
Classifier: License :: OSI Approved :: MIT License
Classifier: Programming Language :: Python :: 3
Classifier: Programming Language :: Python :: 3.6
Classifier: Programming Language :: Python :: 3.7
Classifier: Programming Language :: Python :: 3.8
Classifier: Programming Language :: Python :: 3.9
Classifier: Operating System :: OS Independent
Requires-Python: >=3.6
Requires-Dist: opencv-python>=4.0.0
Requires-Dist: pyautogui>=0.9.0
Requires-Dist: pynput>=1.7.0
Requires-Dist: Pillow>=8.0.0
Requires-Dist: numpy>=1.19.0
Requires-Dist: colorama>=0.4.0
Dynamic: author
Dynamic: author-email
Dynamic: classifier
Dynamic: description
Dynamic: description-content-type
Dynamic: home-page
Dynamic: requires-dist
Dynamic: requires-python
Dynamic: summary
